[{
    "title":"Category title 1",
    "q1": {
        "q": "Question 1",
        "qm": "",
        "a": "Answer",
        "am": ""
    },
    "q2": {
        "q": "Question 2",
        "qm": "",
        "a": "Answer",
        "am": ""
    },
    "q3": {
        "q": "Question 3",
        "qm": "",
        "a": "Answer",
        "am": ""
    },
    "q4": {
        "q": "Question 4",
        "qm": "",
        "a": "Answer",
        "am": ""
    },
},
{
    "title":"Category title 2",
    "q1": {
        "q": "Question",
        "qm": "",
        "a": "Answer",
        "am": ""
    },
    "q2": {
        "q": "Question",
        "qm": "",
        "a": "Answer",
        "am": ""
    },
    "q3": {
        "q": "Question",
        "qm": "",
        "a": "Answer",
        "am": ""
    },
    "q4": {
        "q": "Question",
        "qm": "",
        "a": "Answer",
        "am": ""
    },
},
{
    "title":"Category title 3",
    "q1": {
        "q": "Question",
        "qm": "",
        "a": "Answer",
        "am": ""
    },
    "q2": {
        "q": "Question",
        "qm": "",
        "a": "Answer",
        "am": ""
    },
    "q3": {
        "q": "Question",
        "qm": "",
        "a": "Answer",
        "am": ""
    },
    "q4": {
        "q": "Question",
        "qm": "",
        "a": "Answer",
        "am": ""
    },
},
{
    "title":"Category title 4",
    "q1": {
        "q": "Question",
        "qm": "",
        "a": "Answer",
        "am": ""
    },
    "q2": {
        "q": "Question",
        "qm": "",
        "a": "Answer",
        "am": ""
    },
    "q3": {
        "q": "Question",
        "qm": "",
        "a": "Answer",
        "am": ""
    },
    "q4": {
        "q": "Question",
        "qm": "",
        "a": "Answer",
        "am": ""
    },
},
{
    "title":"Category title 5",
    "q1": {
        "q": "Question",
        "qm": "",
        "a": "Answer",
        "am": ""
    },
    "q2": {
        "q": "Question",
        "qm": "",
        "a": "Answer",
        "am": ""
    },
    "q3": {
        "q": "Question",
        "qm": "",
        "a": "Answer",
        "am": ""
    },
    "q4": {
        "q": "Question",
        "qm": "",
        "a": "Answer",
        "am": ""
    },
},
]
